hfble/__init__.py
hfble-2.0.dist-info/LICENSE.txt
hfble-2.0.dist-info/METADATA
hfble-2.0.dist-info/WHEEL
hfble-2.0.dist-info/top_level.txt
hfble-2.0.dist-info/RECORD
