Metadata-Version: 2.1
Name: hfble
Version: 2.0
Summary: UNKNOWN
Home-page: UNKNOWN
Author: UNKNOWN
Author-email: UNKNOWN
License: MIT License
Platform: UNKNOWN
